deepfake_detection/DeepFake_Utils.py
deepfake_detection/__init__.py
Deep_Fake_Detection-0.0.10.dist-info/LICENCE
Deep_Fake_Detection-0.0.10.dist-info/METADATA
Deep_Fake_Detection-0.0.10.dist-info/WHEEL
Deep_Fake_Detection-0.0.10.dist-info/top_level.txt
Deep_Fake_Detection-0.0.10.dist-info/RECORD
