Metadata-Version: 2.1
Name: Deep-Fake-Detection
Version: 0.0.10
Summary: Deep Fake Detection Project
Home-page: https://github.com/MohamedSebaie/DeepFake-Detection-Using-Pytorch
Author: Mohamed Sebaie
Author-email: mohamedsebaie1@gmail.com
License: UNKNOWN
Platform: UNKNOWN
Classifier: Programming Language :: Python :: 3
Classifier: License :: OSI Approved :: MIT License
Classifier: Operating System :: OS Independent
Requires-Python: >=3.7
License-File: LICENCE
